tumorevo/__init__.py
tumorevo/tumorfig/__init__.py
tumorevo/tumorfig/main.py
tumorevo/tumorfig/util.py
tumorevo/tumorsim/__init__.py
tumorevo/tumorsim/cell.py
tumorevo/tumorsim/deme.py
tumorevo/tumorsim/main.py
tumorevo/tumorsim/modes.py
tumorevo/tumorsim/tumor.py
tumorevo-0.0.1.dist-info/entry_points.txt
tumorevo-0.0.1.dist-info/LICENSE
tumorevo-0.0.1.dist-info/WHEEL
tumorevo-0.0.1.dist-info/METADATA
tumorevo-0.0.1.dist-info/RECORD
