Metadata-Version: 2.1
Name: tumorevo
Version: 0.0.1
Summary: Simulate and illustrate tumor evolution under different spatial constraints.
Home-page: https://github.com/pedrofale/tumorevo
License: MIT
Author: pedrofale
Author-email: pedro.miguel.ferreira.pf@gmail.com
Requires-Python: >=3.7.1,<3.10
Classifier: License :: OSI Approved :: MIT License
Classifier: Programming Language :: Python :: 3
Classifier: Programming Language :: Python :: 3.8
Classifier: Programming Language :: Python :: 3.9
Requires-Dist: click (>=8.0.1,<9.0.0)
Requires-Dist: networkx (>=2.6.2,<3.0.0)
Requires-Dist: numpy (>=1.21.2,<2.0.0)
Requires-Dist: packcircles (>=0.14,<0.15)
Requires-Dist: pandas (>=1.3.2,<2.0.0)
Requires-Dist: pygraphviz (>=1.7,<2.0)
Requires-Dist: pymuller (>=0.1.2,<0.2.0)
Requires-Dist: tqdm (>=4.57.0,<5.0.0)
Project-URL: Repository, https://github.com/pedrofale/tumorevo
